src/benchTrack.py
src/BenchTrack/__init__.py
src/BenchTrack/bench2site.py
src/BenchTrack/generateRst.py
src/BenchTrack/structureBench.py
src/BenchTrack/target.py
src/BenchTrack/task.py
src/BenchTrack/theme.py
src/BenchTrack/tools.py
src/site/__init__.py
src/site/pelicanconf.py
src/site/publishconf.py
src/site/images_content/rect_green.png
src/site/images_content/rect_orange.png
src/site/images_content/rect_red.png
src/site/theme/.gitignore
src/site/theme/.travis.yml
src/site/theme/LICENSE
src/site/theme/.github/FUNDING.yml
src/site/theme/.github/workflows/pelican-publish.yml
src/site/theme/static/font-awesome/css/brands.css
src/site/theme/static/font-awesome/css/fontawesome.css
src/site/theme/static/font-awesome/css/solid.css
src/site/theme/static/font-awesome/webfonts/fa-brands-400.eot
src/site/theme/static/font-awesome/webfonts/fa-brands-400.svg
src/site/theme/static/font-awesome/webfonts/fa-brands-400.ttf
src/site/theme/static/font-awesome/webfonts/fa-brands-400.woff
src/site/theme/static/font-awesome/webfonts/fa-brands-400.woff2
src/site/theme/static/font-awesome/webfonts/fa-solid-900.eot
src/site/theme/static/font-awesome/webfonts/fa-solid-900.svg
src/site/theme/static/font-awesome/webfonts/fa-solid-900.ttf
src/site/theme/static/font-awesome/webfonts/fa-solid-900.woff
src/site/theme/static/font-awesome/webfonts/fa-solid-900.woff2
src/site/theme/static/isso/isso.min.js
src/site/theme/static/pygments/abap.css
src/site/theme/static/pygments/abap.min.css
src/site/theme/static/pygments/algol.css
src/site/theme/static/pygments/algol.min.css
src/site/theme/static/pygments/algol_nu.css
src/site/theme/static/pygments/algol_nu.min.css
src/site/theme/static/pygments/arduino.css
src/site/theme/static/pygments/arduino.min.css
src/site/theme/static/pygments/autumn.css
src/site/theme/static/pygments/autumn.min.css
src/site/theme/static/pygments/borland.css
src/site/theme/static/pygments/borland.min.css
src/site/theme/static/pygments/bw.css
BenchTrack-1.0.1.dist-info/LICENSE.md
BenchTrack-1.0.1.dist-info/METADATA
BenchTrack-1.0.1.dist-info/WHEEL
BenchTrack-1.0.1.dist-info/entry_points.txt
BenchTrack-1.0.1.dist-info/top_level.txt
BenchTrack-1.0.1.dist-info/RECORD
